Metadata-Version: 1.1
Name: periskop
Version: 1.0.0
Summary: Integration testing for ChatOps via Slack
Home-page: https://github.com/unic/periskop
Author: Unic AG - Robert Erdin, Mathias Petermann, Nicolas Baer
Author-email: cloud@unic.com
License: Apache License 2.0
Platform: any
Classifier: Development Status :: 4 - Beta
Classifier: Environment :: Console
Classifier: Intended Audience :: Developers
Classifier: License :: OSI Approved :: Apache Software License
Classifier: Operating System :: POSIX
Classifier: Operating System :: MacOS
Classifier: Operating System :: Unix
Classifier: Programming Language :: Python
Classifier: Programming Language :: Python :: 2
Classifier: Programming Language :: Python :: 3
Classifier: Topic :: Software Development :: Libraries :: Python Modules
